Aduct/Element.py
Aduct/Provider.py
Aduct/__init__.py
Aduct/Views/Bin.py
Aduct/Views/Notebook.py
Aduct/Views/Paned.py
Aduct/Views/View.py
Aduct/Views/__init__.py
Aduct-1.2.0.dist-info/COPYING
Aduct-1.2.0.dist-info/COPYING.LESSER
Aduct-1.2.0.dist-info/METADATA
Aduct-1.2.0.dist-info/WHEEL
Aduct-1.2.0.dist-info/top_level.txt
Aduct-1.2.0.dist-info/RECORD
