Metadata-Version: 2.1
Name: Aduct
Version: 1.2.0
Summary: Aduct lets you make flexible interfaces that can be easily    improved and modified by both developers and users.
Home-page: https://github.com/atornel/Aduct
Author: J Arun Mani; Atornel
Author-email: j.arunmani@protonmail.com
License: UNKNOWN
Keywords: gui gtk ui
Platform: UNKNOWN
Classifier: Development Status :: 5 - Production/Stable
Classifier: Intended Audience :: Developers
Classifier: License :: OSI Approved :: GNU Lesser General Public License v3 or later (LGPLv3+)
Classifier: Operating System :: Microsoft :: Windows
Classifier: Operating System :: POSIX
Classifier: Programming Language :: Python :: 3
Classifier: Topic :: Software Development
Requires-Python: ~=3.3
Requires-Dist: pygobject
